setup.py
SWHT/Ylm.py
SWHT/__init__.py
SWHT/display.py
SWHT/ecef.py
SWHT/fileio.py
SWHT/ft.py
SWHT/lofarConfig.py
SWHT/swht.py
SWHT/util.py
SWHT.egg-info/PKG-INFO
SWHT.egg-info/SOURCES.txt
SWHT.egg-info/dependency_links.txt
SWHT.egg-info/top_level.txt
SWHT/data/LOFAR/HBAtile.txt
SWHT/data/LOFAR/StaticMetaData/AntennaArrays_CS.conf
SWHT/data/LOFAR/StaticMetaData/AntennaArrays_Int.conf
SWHT/data/LOFAR/StaticMetaData/AntennaArrays_RS.conf
SWHT/data/LOFAR/StaticMetaData/AntennaArrays_default.conf
SWHT/data/LOFAR/StaticMetaData/CS001-AntennaArrays.conf
SWHT/data/LOFAR/StaticMetaData/CS001-AntennaField.conf
SWHT/data/LOFAR/StaticMetaData/CS001-CableDelays.conf
SWHT/data/LOFAR/StaticMetaData/CS001-HBADeltas.conf
SWHT/data/LOFAR/StaticMetaData/CS001-iHBADeltas.conf
SWHT/data/LOFAR/StaticMetaData/CS002-AntennaArrays.conf
SWHT/data/LOFAR/StaticMetaData/CS002-AntennaField.conf
SWHT/data/LOFAR/StaticMetaData/CS002-CableDelays.conf
SWHT/data/LOFAR/StaticMetaData/CS002-HBADeltas.conf
SWHT/data/LOFAR/StaticMetaData/CS002-iHBADeltas.conf
SWHT/data/LOFAR/StaticMetaData/CS003-AntennaArrays.conf
SWHT/data/LOFAR/StaticMetaData/CS003-AntennaField.conf
SWHT/data/LOFAR/StaticMetaData/CS003-CableDelays.conf
SWHT/data/LOFAR/StaticMetaData/CS003-HBADeltas.conf
SWHT/data/LOFAR/StaticMetaData/CS003-iHBADeltas.conf
SWHT/data/LOFAR/StaticMetaData/CS004-AntennaArrays.conf
SWHT/data/LOFAR/StaticMetaData/CS004-AntennaField.conf
SWHT/data/LOFAR/StaticMetaData/CS004-CableDelays.conf
SWHT/data/LOFAR/StaticMetaData/CS004-HBADeltas.conf
SWHT/data/LOFAR/StaticMetaData/CS004-iHBADeltas.conf
SWHT/data/LOFAR/StaticMetaData/CS005-AntennaArrays.conf
SWHT/data/LOFAR/StaticMetaData/CS005-AntennaField.conf
SWHT/data/LOFAR/StaticMetaData/CS005-CableDelays.conf
SWHT/data/LOFAR/StaticMetaData/CS005-HBADeltas.conf
SWHT/data/LOFAR/StaticMetaData/CS005-iHBADeltas.conf
SWHT/data/LOFAR/StaticMetaData/CS006-AntennaArrays.conf
SWHT/data/LOFAR/StaticMetaData/CS006-AntennaField.conf
SWHT/data/LOFAR/StaticMetaData/CS006-CableDelays.conf
SWHT/data/LOFAR/StaticMetaData/CS006-HBADeltas.conf
