Metadata-Version: 1.1
Name: SWHT
Version: 0.1.2
Summary: Spherical Wave Harmonic Transform for radio astronomy visibility data
Home-page: https://github.com/griffinfoster/SWHT
Author: Griffin Foster
Author-email: griffin.foster@gmail.com
License: GPL
Platform: *nix
Classifier: Development Status :: 4 - Beta
Classifier: Environment :: Console
Classifier: Natural Language :: English
Classifier: Operating System :: POSIX :: Linux
Classifier: Programming Language :: Python :: 2.7
Classifier: Intended Audience :: Science/Research
Classifier: License :: OSI Approved :: GNU General Public License (GPL)
Classifier: Topic :: Scientific/Engineering :: Astronomy
Requires: distutils
Requires: numpy
Requires: scipy
Requires: matplotlib
Requires: healpy
Requires: ephem
Provides: SWHT
